proxynorm/__init__.py
proxynorm-0.1.0.dist-info/METADATA
proxynorm-0.1.0.dist-info/WHEEL
proxynorm-0.1.0.dist-info/top_level.txt
proxynorm-0.1.0.dist-info/RECORD
